lightning_disk_kv-1.1.1.dist-info/METADATA
lightning_disk_kv-1.1.1.dist-info/WHEEL
lightning_disk_kv/__init__.py
lightning_disk_kv/lightning_disk_kv.abi3.so
lightning_redis.py
lightning_disk_kv-1.1.1.dist-info/RECORD
