Metadata-Version: 2.4
Name: lightning_disk_kv
Version: 1.1.1
Classifier: Programming Language :: Rust
Classifier: Programming Language :: Python :: Implementation :: CPython
Classifier: Programming Language :: Python :: Implementation :: PyPy
Classifier: Programming Language :: Python :: 3
Classifier: License :: OSI Approved :: MIT License
Classifier: Operating System :: POSIX :: Linux
Classifier: Operating System :: Microsoft :: Windows
Classifier: Operating System :: MacOS
Requires-Dist: numpy
Summary: "Disk-based redis" - Built around LMDB and Rust, with sharding for maximum throughput
Author-email: Carlo Moro <cnmoro@gmail.com>
Requires-Python: >=3.8
Project-URL: Repository, https://github.com/cnmoro/lightning-disk-kv
